rayyan_store/__init__.py
rayyan_store/rayyan_store.py
rayyan_store-0.2.0.dist-info/METADATA
rayyan_store-0.2.0.dist-info/WHEEL
rayyan_store-0.2.0.dist-info/top_level.txt
rayyan_store-0.2.0.dist-info/RECORD
