Metadata-Version: 2.1
Name: rayyan-store
Version: 0.2.0
Summary: Python client interface for RayyanStore
Author: Fadhil Abubaker
Requires-Dist: requests
